partcad_cli/__init__.py
partcad_cli/click/__init__.py
partcad_cli/click/cli_context.py
partcad_cli/click/command.py
partcad_cli/click/loader.py
partcad_cli/click/commands/__init__.py
partcad_cli/click/commands/config.py
partcad_cli/click/commands/convert.py
partcad_cli/click/commands/export.py
partcad_cli/click/commands/healthcheck.py
partcad_cli/click/commands/info.py
partcad_cli/click/commands/init.py
partcad_cli/click/commands/inspect.py
partcad_cli/click/commands/install.py
partcad_cli/click/commands/render.py
partcad_cli/click/commands/test.py
partcad_cli/click/commands/update.py
partcad_cli/click/commands/version.py
partcad_cli/click/commands/add/__init__.py
partcad_cli/click/commands/add/assembly.py
partcad_cli/click/commands/add/dep.py
partcad_cli/click/commands/add/part.py
partcad_cli/click/commands/add/sketch.py
partcad_cli/click/commands/adhoc/__init__.py
partcad_cli/click/commands/adhoc/convert.py
partcad_cli/click/commands/ai/__init__.py
partcad_cli/click/commands/ai/regenerate.py
partcad_cli/click/commands/import/__init__.py
partcad_cli/click/commands/import/assembly.py
partcad_cli/click/commands/import/part.py
partcad_cli/click/commands/list/__init__.py
partcad_cli/click/commands/list/all.py
partcad_cli/click/commands/list/assemblies.py
partcad_cli/click/commands/list/interfaces.py
partcad_cli/click/commands/list/mates.py
partcad_cli/click/commands/list/packages.py
partcad_cli/click/commands/list/parts.py
partcad_cli/click/commands/list/sketches.py
partcad_cli/click/commands/supply/__init__.py
partcad_cli/click/commands/supply/caps.py
partcad_cli/click/commands/supply/find.py
partcad_cli/click/commands/supply/order.py
partcad_cli/click/commands/supply/quote.py
partcad_cli/click/commands/system/__init__.py
partcad_cli/click/commands/system/reset.py
partcad_cli/click/commands/system/status.py
partcad_cli/click/commands/system/set/__init__.py
partcad_cli/click/commands/system/set/telemetry/__init__.py
partcad_cli-0.7.135.dist-info/METADATA
partcad_cli-0.7.135.dist-info/WHEEL
partcad_cli-0.7.135.dist-info/entry_points.txt
partcad_cli-0.7.135.dist-info/top_level.txt
partcad_cli-0.7.135.dist-info/RECORD
