Metadata-Version: 2.4
Name: partcad-cli
Version: 0.7.135
Summary: Command-line interface to PartCAD
Author-email: PartCAD <support@partcad.org>
Maintainer-email: PartCAD <support@partcad.org>
Project-URL: Homepage, https://github.com/partcad/partcad
Project-URL: Issues, https://github.com/partcad/partcad/issues
Keywords: cadquery,build123d,cad,design,openscad,step,stl
Classifier: Programming Language :: Python :: 3
Classifier: License :: OSI Approved :: Apache Software License
Classifier: Operating System :: OS Independent
Requires-Python: <3.13,>=3.10
Requires-Dist: click
Requires-Dist: ocp_vscode
Requires-Dist: partcad==0.7.135
Requires-Dist: rich-click==1.8.5
